spice_agent/__init__.py
spice_agent/__version__.py
spice_agent/auth/__init__.py
spice_agent/auth/actions.py
spice_agent/auth/commands.py
spice_agent/cli.py
spice_agent/client.py
spice_agent/daemons/__init__.py
spice_agent/daemons/actions.py
spice_agent/daemons/commands.py
spice_agent/daemons/launch_agents.py
spice_agent/daemons/launch_service.py
spice_agent/graphql/__init__.py
spice_agent/graphql/documents/__init__.py
spice_agent/graphql/documents/authentication.gql
spice_agent/graphql/sdk.py
spice_agent/hardware/__init__.py
spice_agent/hardware/actions.py
spice_agent/hardware/commands.py
spice_agent/inference/__init__.py
spice_agent/inference/actions.py
spice_agent/inference/commands.py
spice_agent/inference/tasks.py
spice_agent/inference/types.py
spice_agent/tests/__init__.py
spice_agent/tests/test_memory_size.py
spice_agent/tests/test_version.py
spice_agent/training/__init__.py
spice_agent/training/actions.py
spice_agent/training/commands.py
spice_agent/uploader/actions.py
spice_agent/utils/__init__.py
spice_agent/utils/config.py
spice_agent/utils/memory_size.py
spice_agent/utils/printer.py
spice_agent/utils/updates.py
spice_agent/utils/version.py
spice_agent/worker/__init__.py
spice_agent/worker/actions.py
spice_agent/worker/commands.py
spice_agent-0.1.18.dist-info/METADATA
spice_agent-0.1.18.dist-info/WHEEL
spice_agent-0.1.18.dist-info/entry_points.txt
spice_agent-0.1.18.dist-info/RECORD
