Metadata-Version: 2.1
Name: spice_agent
Version: 0.1.18
Summary: spice agent
Author: Dylan Stein
Author-email: dylan@spice.cloud
Requires-Python: >=3.11.3,<4.0.0
Classifier: Programming Language :: Python :: 3
Requires-Dist: accelerate (>=0.20.3,<0.21.0)
Requires-Dist: aiohttp (>=3.8.4,<4.0.0)
Requires-Dist: boto3 (>=1.26.165,<2.0.0)
Requires-Dist: click (>=8.1.3,<9.0.0)
Requires-Dist: compel (>=2.0.1,<3.0.0)
Requires-Dist: datasets (>=2.13.1,<3.0.0)
Requires-Dist: diffusers (==0.20.2)
Requires-Dist: evaluate (>=0.4.0,<0.5.0)
Requires-Dist: gql (>=3.4.1,<4.0.0)
Requires-Dist: invisible-watermark (>=0.2.0,<0.3.0)
Requires-Dist: numpy (>=1.25.0,<2.0.0)
Requires-Dist: outdated (>=0.2.2,<0.3.0)
Requires-Dist: pika (>=1.3.1,<2.0.0)
Requires-Dist: psutil (>=5.9.5,<6.0.0)
Requires-Dist: retry (>=0.9.2,<0.10.0)
Requires-Dist: scikit-learn (>=1.2.2,<2.0.0)
Requires-Dist: sentry-sdk (>=1.24.0,<2.0.0)
Requires-Dist: torch (>=2.0.1,<3.0.0)
Requires-Dist: torchvision (>=0.15.2,<0.16.0)
Requires-Dist: transformers (>=4.30.2,<5.0.0)
